bedrock_a_bot/__init__.py
bedrock_a_bot/__main__.py
bedrock_a_bot/aws_bedrock.py
bedrock_a_bot/file_upload_handler.py
bedrock_a_bot/logging_config.py
bedrock_a_bot/message_handling.py
bedrock_a_bot/pdf_processing.py
bedrock_a_bot/session_management.py
bedrock_a_bot/sidebar_components.py
bedrock_a_bot/streamlit_chatbot.py
bedrock_a_bot/ui_components.py
bedrock_a_bot/utils.py
bedrock_a_bot-1.0.4.dist-info/METADATA
bedrock_a_bot-1.0.4.dist-info/WHEEL
bedrock_a_bot-1.0.4.dist-info/entry_points.txt
bedrock_a_bot-1.0.4.dist-info/top_level.txt
bedrock_a_bot-1.0.4.dist-info/RECORD
