Metadata-Version: 2.1
Name: bedrock-a-bot
Version: 1.0.4
Summary: A chatbot tool using AWS Bedrock and Streamlit
Home-page: https://github.com/manav148/Bedrock-A-Bot
Author: Manav Kundra
Author-email: your.email@example.com
Classifier: Programming Language :: Python :: 3
Classifier: License :: OSI Approved :: MIT License
Classifier: Operating System :: OS Independent
Requires-Python: >=3.12
Requires-Dist: streamlit
Requires-Dist: boto3
Requires-Dist: tiktoken
Requires-Dist: PyPDF2
